Verilog/Capitulo_4/Deco_2_a_4/Deco_2_4.v
//Descripcion a nivel de compuertas de un decodificador de dos a cuatro lineas

module decoder_2x4_gates (D, A, B, enable);

    output [0:3] D;
    input A, B, enable;
    wire A_not, B_not, enable_not;

    not
        G1 (A_not, A),
        G2 (B_not, B),
        G3 (enable_not, enable);

    nand
        G4 (D[0], A_not, B_not, enable_not),
        G5 (D[1], A_not, B, enable_not),
        G6 (D[2], A, B_not, enable_not),
        G7 (D[3], A, B, enable_not);

endmodule

Verilog/Capitulo_4/Deco_2_a_4/t_Deco_2_4.v
//Banco de pruebas para un decodificador de dos a cuatro líneas

`timescale 1ns / 1ps

module t_Decoder_2x4_gates;

    wire [0:3] D;
    reg A, B, enable;
    decoder_2x4_gates M1 (D, A, B, enable);


    initial begin
	
	$dumpfile("t_Decoder_2x4_gates.vcd");
	$dumpvars(0, t_Decoder_2x4_gates);
		
        enable = 1'b0; A = 1'b0; B = 1'b0;
        #100 enable = 1'b0; A = 1'b0; B = 1'b1;
        #100 enable = 1'b0; A = 1'b1; B = 1'b0;
        #100 enable = 1'b0; A = 1'b1; B = 1'b1;
        #100 enable = 1'b1; A = 1'b0; B = 1'b0;
        #100 enable = 1'b1; A = 1'b0; B = 1'b1;
        #100 enable = 1'b1; A = 1'b1; B = 1'b0;
        #100 enable = 1'b1; A = 1'b1; B = 1'b1;
    end

    initial #1000 $finish;

endmodule

Verilog/Capitulo_4/Deco_2_a_4/t_Decoder_2x4_gates.vcd
$date
	Tue Jul 20 09:59:41 2021
$end
$version
	Icarus Verilog
$end
$timescale
	1ps
$end
$scope module t_Decoder_2x4_gates $end
$var wire 4 ! D [0:3] $end
$var reg 1 " A $end
$var reg 1 # B $end
$var reg 1 $ enable $end
$scope module M1 $end
$var wire 1 " A $end
$var wire 1 % A_not $end
$var wire 1 # B $end
$var wire 1 & B_not $end
$var wire 1 $ enable $end
$var wire 1 ' enable_not $end
$var wire 4 ( D [0:3] $end
$upscope $end
$upscope $end
$enddefinitions $end
#0
$dumpvars
b111 (
1'
1&
1%
0$
0#
0"
b111 !
$end
#100000
0&
b1011 !
b1011 (
1#
#200000
1&
b1101 !
b1101 (
0%
0#
1"
#300000
0&
b1110 !
b1110 (
1#
#400000
1&
1%
b1111 !
b1111 (
0'
0#
0"
1$
#500000
0&
1#
#600000
1&
0%
0#
1"
#700000
0&
1#
